legistream_backend/__init__.py
legistream_backend/act.py
legistream_backend/common.py
legistream_backend/federal.py
legistream_backend/nsw.py
legistream_backend/nt.py
legistream_backend/qld.py
legistream_backend/sa.py
legistream_backend/tas.py
legistream_backend/util/fileutils.py
legistream_backend/vic.py
legistream_backend/wa.py
legistream_backend-1.4.17.dist-info/LICENSE
legistream_backend-1.4.17.dist-info/WHEEL
legistream_backend-1.4.17.dist-info/METADATA
legistream_backend-1.4.17.dist-info/RECORD
