Metadata-Version: 2.1
Name: legistream-backend
Version: 1.4.17
Summary: Get live stream metadata from the various Australian parliaments.
Home-page: https://legistream.org
License: GPL-2.0-only
Author: king-millez
Author-email: millez.dev@gmail.com
Requires-Python: >=3.9,<4.0
Classifier: License :: OSI Approved :: GNU General Public License v2 (GPLv2)
Classifier: Programming Language :: Python :: 3
Classifier: Programming Language :: Python :: 3.9
Requires-Dist: ImageHash (>=4.2.0,<5.0.0)
Requires-Dist: bs4 (>=0.0.1,<0.0.2)
Requires-Dist: lxml (>=4.6.3,<5.0.0)
Requires-Dist: m3u8 (>=0.9.0,<0.10.0)
Requires-Dist: pytest (>=6.2.4,<7.0.0)
Requires-Dist: requests (>=2.25.1,<3.0.0)
Requires-Dist: websocket (>=0.2.1,<0.3.0)
Requires-Dist: websocket-client (>=1.1.0,<2.0.0)
